hiding/__init__.py
hiding/hiding.py
hiding-0.0.8.dist-info/LICENSE
hiding-0.0.8.dist-info/METADATA
hiding-0.0.8.dist-info/WHEEL
hiding-0.0.8.dist-info/top_level.txt
hiding-0.0.8.dist-info/RECORD
