Metadata-Version: 2.1
Name: hiding
Version: 0.0.8
Summary: Hiding text in other text.
Home-page: https://github.com/johnngnky/hiding
Author: johnngnky
Author-email: contact@johnngnky.xyz
License: "WTFPL"
Project-URL: Bug Tracker, https://github.com/johnngnky/hiding/issues
Platform: UNKNOWN
Classifier: Programming Language :: Python :: 3
Classifier: Operating System :: OS Independent
Requires-Python: >=3.5
